vdomify/__init__.py
vdomify/_version.py
vdomify/core.py
vdomify/transforms.py
vdomify-0.2.dist-info/DESCRIPTION.rst
vdomify-0.2.dist-info/METADATA
vdomify-0.2.dist-info/RECORD
vdomify-0.2.dist-info/WHEEL
vdomify-0.2.dist-info/metadata.json
vdomify-0.2.dist-info/top_level.txt
