Metadata-Version: 2.0
Name: vdomify
Version: 0.2
Summary: vdomify objects
Home-page: https://github.com/rgbkrk/vdomify
Author: nteract contributors
Author-email: jupyter@googlegroups.com
License: BSD
Keywords: vdom,html
Platform: UNKNOWN
Requires-Dist: vdom
